MANIFEST.in
README
bitis.py
setup.cfg
setup.py
bitis.egg-info/PKG-INFO
bitis.egg-info/SOURCES.txt
bitis.egg-info/dependency_links.txt
bitis.egg-info/top_level.txt
doc/btsformat.rst
doc/changelog.rst
doc/conf.py
doc/contents.rst
doc/examples.rst
doc/index.rst
doc/intro.rst
doc/moduleref.rst
examples/.directory
examples/__init__.py
examples/c2.py
examples/correlation.png
examples/correlation.py
examples/lockin.png
examples/lockin.py
examples/modem.py
examples/modem1.png
examples/modem2.png
examples/modem3.png
examples/p.py
examples/plot.png
examples/plot.py
examples/plot.txt
examples/serial_tx.png
examples/serial_tx.py
examples/xor_logic.py
test/test.py
test/test_examples.py