Metadata-Version: 1.1
Name: bitis
Version: 0.12.3
Summary: Bitis is a processing library for binary timed signals
Home-page: http://bitis.inrim.it
Author: Fabrizio Pollastri
Author-email: f.pollastri@inrim.it
License: http://www.gnu.org/licenses/gpl.txt
Platform: Linux
Classifier: Development Status :: 3 - Alpha
Classifier: Intended Audience :: Developers
Classifier: License :: OSI Approved :: GNU General Public License (GPL)
Classifier: Programming Language :: Python
Classifier: Topic :: Scientific/Engineering
Classifier: Topic :: Software Development :: Libraries :: Python Modules
Classifier: Operating System :: POSIX :: Linux
